tman/__init__.py
tman/api.py
tman/backend/__init__.py
tman/cli/__init__.py
tman/cli/main.py
tman/gui/__init__.py
tman/gui/main.py
tman/util/__init__.py
tman/util/logging.py
tman-0.0.1.dist-info/entry_points.txt
tman-0.0.1.dist-info/LICENSE
tman-0.0.1.dist-info/WHEEL
tman-0.0.1.dist-info/METADATA
tman-0.0.1.dist-info/RECORD
