Metadata-Version: 2.1
Name: tman
Version: 0.0.1
Summary: TODO
Home-page: https://github.com/Danmou/TMan
License: GPL-3.0-only
Author: Daniel Mouritzen
Author-email: dmrtzn@gmail.com
Requires-Python: >=3.10.0,<4.0
Classifier: Development Status :: 2 - Pre-Alpha
Classifier: Intended Audience :: Developers
Classifier: License :: OSI Approved :: GNU General Public License v3 (GPLv3)
Classifier: Natural Language :: English
Classifier: Programming Language :: Python :: 3
Classifier: Programming Language :: Python :: 3.10
Provides-Extra: dev
Provides-Extra: doc
Provides-Extra: test
Requires-Dist: PySimpleGUI (>=4.49.0,<5.0.0)
Requires-Dist: appdirs (>=1.4.4,<2.0.0)
Requires-Dist: attrs (>=21.2.0,<22.0.0)
Requires-Dist: black (>=21.5b2,<22.0); extra == "test"
Requires-Dist: bump2version (>=1.0.1,<2.0.0); extra == "dev"
Requires-Dist: click (>=8.0.1,<9.0.0)
Requires-Dist: flake8 (>=4.0.1,<5.0.0); extra == "test"
Requires-Dist: flake8-docstrings (>=1.6.0,<2.0.0); extra == "test"
Requires-Dist: hypothesis (>=6.23.2,<7.0.0); extra == "test"
Requires-Dist: isort (>=5.8.0,<6.0.0); extra == "test"
Requires-Dist: loguru (>=0.5.3,<0.6.0)
Requires-Dist: mkdocs (>=1.1.2,<2.0.0); extra == "doc"
Requires-Dist: mkdocs-autorefs (>=0.3.0,<0.4.0); extra == "doc"
Requires-Dist: mkdocs-include-markdown-plugin (>=3.2.3,<4.0.0); extra == "doc"
Requires-Dist: mkdocs-material (>=7.3.3,<8.0.0); extra == "doc"
Requires-Dist: mkdocs-material-extensions (>=1.0.1,<2.0.0); extra == "doc"
Requires-Dist: mkdocstrings (>=0.16.2,<0.17.0); extra == "doc"
Requires-Dist: mypy (>=0.910,<0.911); extra == "test"
Requires-Dist: pip (>=20.3.1,<21.0.0); extra == "dev"
Requires-Dist: pre-commit (>=2.12.0,<3.0.0); extra == "dev"
Requires-Dist: pydantic (>=1.8.2,<2.0.0)
Requires-Dist: pytest (>=6.2.4,<7.0.0); extra == "test"
Requires-Dist: pytest-cov (>=3.0.0,<4.0.0); extra == "test"
Requires-Dist: toml (>=0.10.2,<0.11.0); extra == "dev"
Requires-Dist: tox (>=3.20.1,<4.0.0); extra == "dev"
Requires-Dist: twine (>=3.3.0,<4.0.0); extra == "dev"
Requires-Dist: types-appdirs (>=1.4.1,<2.0.0); extra == "test"
Requires-Dist: types-attrs (>=19.1.0,<20.0.0); extra == "test"
Requires-Dist: types-click (>=7.1.7,<8.0.0); extra == "test"
Requires-Dist: types-setuptools (>=57.4.2,<58.0.0); extra == "test"
Requires-Dist: virtualenv (>=20.2.2,<21.0.0); extra == "dev"
